{
  "positions": {
    "cropEnd": [276, 56, 329],
    "defaultStart": [220, 56, 330]
  },
  "scriptConfig": {
    "activeCrop": null
  },
  "chests": {
    "soil": {
      "supply": [220, 55, 397],
      "dump": [220, 58, 398]
    },
    "fertilizer": {
      "supply": [221, 55, 397],
      "dump": [222, 58, 399]
    },
    "seeds": {
      "supply": [220, 55, 397],
      "dump": [220, 57, 398]
    },
    "water": {
      "supply": [207, 56, 397]
    }
  },
  "seedsByCrop": {
    "apple": {
      "supply": [216, 54, 396],
      "dump": [216, 58, 398]
    },
    "mango": {
      "supply": [215, 54, 396],
      "dump": [215, 58, 398]
    },
      "banana": {
        "supply": [214, 54, 396],
        "dump": [214, 58, 398]
      }
    },
  "purchase": {
    "maxTrips": 3,
    "jeckyl": {
      "teleportCommand": "/balloon yellow-balloon",
      "pos1": [-75, 69, -133],
      "pos2": [-80, 71, -141],
      "interactPos": [-80, 71, -141]
    },
    "seedShop": {
      "teleportCommand": "/balloon yellow-balloon",
      "pos1": [-54, 69, -119],
      "pos2": [-57, 71, -115],
      "interactPos": [-57, 71, -115],
      "nextPageName": "Next Page"
    }
  },
  "items": {
    "soil": ["Bag o' Soil"],
    "fertilizer": ["Produce Multiplier Fertilizer"],
    "seeds": [],
    "water": ["Wooden Watering Can"],
    "refillTrigger": "Paper",
    "transferList": ["Bag o' Soil", "Produce Multiplier Fertilizer"]
  },

  "keybindings": {
    "close": "key.keyboard.x",
    "pause": "key.keyboard.z",
    "sprint": "key.forward",
    "forward": "key.sprint",
    "rightClick": "key.mouse.right",
    "leftClick": "key.mouse.left",
    "modeSoil": "key.keyboard.1",
    "modeFertilize": "key.keyboard.2",
    "modePlant": "key.keyboard.3",
    "modeWater": "key.keyboard.4"
  },
  "timings": {
    "containerWaitTimeout": 100,
    "containerOpenRetries": 2,
    "eatWaitTicks": 66,
    "postEatWaitTicks": 20,
    "chestWaitTicks": 34,
    "invCloseWaitTicks": 6,
    "attackWaitTicks": 1,
    "moveWaitTicks": 1,
    "refillWaitTicks": 16,
    "fertilizeWaitTicks": 1,

    "teleportWait": 134,
    "npcInteractWait": 14,
    "npcSecondInteractWait": 14,

    "lookSmoothSpeed": 0.2,
    "lookSmoothSpeedMin": 0.12,
    "lookSmoothSpeedMax": 0.45
  },
  "thresholds": {
    "stepSize": 5,
    "refillThreshold": 6,
    "foodLevel": 20,
    "playerReach": 3,
    "stuckJumpThreshold": 20,
    "lookTurnOnlyAngle": 35,
    "lookSlowdownAngle": 18,
    "lookSpeedAngleRange": 90,
    "lookJitterAngle": 0.4,
    "lookJitterCutoff": 12,
    "lookPitchLag": 0.7
  },


  "constants": {
    "maxInventorySlots": 36,
    "maxStackSize": 64
  }
}
